flytekitplugins_identity_aware_proxy-1.16.12-py3.14-nspkg.pth
flytekitplugins/identity_aware_proxy/__init__.py
flytekitplugins/identity_aware_proxy/cli.py
flytekitplugins_identity_aware_proxy-1.16.12.dist-info/METADATA
flytekitplugins_identity_aware_proxy-1.16.12.dist-info/WHEEL
flytekitplugins_identity_aware_proxy-1.16.12.dist-info/entry_points.txt
flytekitplugins_identity_aware_proxy-1.16.12.dist-info/namespace_packages.txt
flytekitplugins_identity_aware_proxy-1.16.12.dist-info/top_level.txt
flytekitplugins_identity_aware_proxy-1.16.12.dist-info/RECORD
