Metadata-Version: 2.4
Name: flytekitplugins-identity_aware_proxy
Version: 1.16.12
Summary: External command plugin to generate ID tokens for GCP Identity Aware Proxy
Home-page: https://github.com/flyteorg/flytekit/tree/master/plugins/flytekit-identity-aware-proxy
Author: flyteorg
Author-email: admin@flyte.org
License: apache2
Classifier: Intended Audience :: Science/Research
Classifier: Intended Audience :: Developers
Classifier: License :: OSI Approved :: Apache Software License
Classifier: Programming Language :: Python :: 3.8
Classifier: Programming Language :: Python :: 3.9
Classifier: Programming Language :: Python :: 3.10
Classifier: Topic :: Scientific/Engineering
Classifier: Topic :: Scientific/Engineering :: Artificial Intelligence
Classifier: Topic :: Software Development
Classifier: Topic :: Software Development :: Libraries
Classifier: Topic :: Software Development :: Libraries :: Python Modules
Requires-Python: >=3.8
Requires-Dist: click
Requires-Dist: google-cloud-secret-manager
Requires-Dist: google-auth
Requires-Dist: flytekit>=1.10
Requires-Dist: grpcio>=1.62.0
Dynamic: author
Dynamic: author-email
Dynamic: classifier
Dynamic: description
Dynamic: description-content-type
Dynamic: home-page
Dynamic: license
Dynamic: requires-dist
Dynamic: requires-python
Dynamic: summary
